keepy/__init__.py
keepy-0.0.1a0.dist-info/WHEEL
keepy-0.0.1a0.dist-info/METADATA
keepy-0.0.1a0.dist-info/RECORD
